airflow_provider_openmetadata/__init__.py
airflow_provider_openmetadata/lineage/__init__.py
airflow_provider_openmetadata/lineage/openmetadata.py
build/lib/airflow_provider_openmetadata/__init__.py
build/lib/airflow_provider_openmetadata/lineage/__init__.py
build/lib/airflow_provider_openmetadata/lineage/openmetadata.py
build/lib/env/bin/rst2html.py
build/lib/env/bin/rst2html4.py
build/lib/env/bin/rst2html5.py
build/lib/env/bin/rst2latex.py
build/lib/env/bin/rst2man.py
build/lib/env/bin/rst2odt.py
build/lib/env/bin/rst2odt_prepstyles.py
build/lib/env/bin/rst2pseudoxml.py
build/lib/env/bin/rst2s5.py
build/lib/env/bin/rst2xetex.py
build/lib/env/bin/rst2xml.py
build/lib/env/bin/rstpep2html.py
build/lib/metadata/__init__.py
build/lib/metadata/cmd.py
build/lib/metadata/config/__init__.py
build/lib/metadata/config/common.py
build/lib/metadata/generated/data/tags/__init__.py
build/lib/metadata/generated/data/tags/personalDataTags.py
build/lib/metadata/generated/data/tags/piiTags.py
build/lib/metadata/generated/data/tags/tierTags.py
build/lib/metadata/generated/data/tags/userTags.py
build/lib/metadata/generated/schema/api/__init__.py
build/lib/metadata/generated/schema/api/catalogVersion.py
build/lib/metadata/generated/schema/api/setOwner.py
build/lib/metadata/generated/schema/api/data/__init__.py
build/lib/metadata/generated/schema/api/data/createChart.py
build/lib/metadata/generated/schema/api/data/createDashboard.py
build/lib/metadata/generated/schema/api/data/createDatabase.py
build/lib/metadata/generated/schema/api/data/createModel.py
build/lib/metadata/generated/schema/api/data/createPipeline.py
build/lib/metadata/generated/schema/api/data/createTable.py
build/lib/metadata/generated/schema/api/data/createTask.py
build/lib/metadata/generated/schema/api/data/createTopic.py
build/lib/metadata/generated/schema/api/feed/__init__.py
build/lib/metadata/generated/schema/api/feed/createThread.py
build/lib/metadata/generated/schema/api/lineage/__init__.py
openmetadata_airflow-1.0.dist-info/METADATA
openmetadata_airflow-1.0.dist-info/WHEEL
openmetadata_airflow-1.0.dist-info/entry_points.txt
openmetadata_airflow-1.0.dist-info/top_level.txt
openmetadata_airflow-1.0.dist-info/RECORD
