Metadata-Version: 2.1
Name: openmetadata-airflow
Version: 1.0
Summary: Python Distribution Utilities
Home-page: UNKNOWN
License: UNKNOWN
Platform: UNKNOWN
